ipapocket/__init__.py
ipapocket/exceptions/__init__.py
ipapocket/exceptions/ccache.py
ipapocket/exceptions/exceptions.py
ipapocket/exceptions/krb5.py
ipapocket/krb5/__init__.py
ipapocket/krb5/asn1.py
ipapocket/krb5/ccache.py
ipapocket/krb5/constants.py
ipapocket/krb5/fields.py
ipapocket/krb5/objects.py
ipapocket/krb5/operations.py
ipapocket/krb5/crypto/__init__.py
ipapocket/krb5/crypto/backend.py
ipapocket/krb5/crypto/crypto.py
ipapocket/krb5/crypto/sp800.py
ipapocket/krb5/crypto/utils.py
ipapocket/krb5/types/__init__.py
ipapocket/krb5/types/enc_types.py
ipapocket/krb5/types/encrypted_data.py
ipapocket/krb5/types/host_address.py
ipapocket/krb5/types/host_addresses.py
ipapocket/krb5/types/int32.py
ipapocket/krb5/types/kdc_options.py
ipapocket/krb5/types/kdc_req_body.py
ipapocket/krb5/types/kerberos_flags.py
ipapocket/krb5/types/kerberos_string.py
ipapocket/krb5/types/kerberos_strings.py
ipapocket/krb5/types/kerberos_time.py
ipapocket/krb5/types/microseconds.py
ipapocket/krb5/types/principal_name.py
ipapocket/krb5/types/realm.py
ipapocket/krb5/types/ticket.py
ipapocket/krb5/types/ticket_flags.py
ipapocket/krb5/types/tickets.py
ipapocket/krb5/types/uint32.py
ipapocket/network/__init__.py
ipapocket/network/krb5.py
ipapocket/utils/__init__.py
ipapocket/utils/logger.py
ipapocket-0.2.data/scripts/ipp-cve-2024-3183.py
ipapocket-0.2.data/scripts/ipp-get-tgs.py
ipapocket-0.2.data/scripts/ipp-get-tgt.py
ipapocket-0.2.data/scripts/ipp-renew-ticket.py
ipapocket-0.2.data/scripts/ipp-show-ccache.py
ipapocket-0.2.data/scripts/ipp-user-enum.py
ipapocket-0.2.dist-info/LICENSE
ipapocket-0.2.dist-info/METADATA
ipapocket-0.2.dist-info/WHEEL
ipapocket-0.2.dist-info/top_level.txt
ipapocket-0.2.dist-info/RECORD
